__init__.py
databricks_dbt_factory/DbtFactory.py
databricks_dbt_factory/DbtTask.py
databricks_dbt_factory/SpecsHandler.py
databricks_dbt_factory/TaskFactory.py
databricks_dbt_factory/Utils.py
databricks_dbt_factory/__about__.py
databricks_dbt_factory/__init__.py
databricks_dbt_factory/main.py
databricks_dbt_factory-0.1.1.dist-info/METADATA
databricks_dbt_factory-0.1.1.dist-info/WHEEL
databricks_dbt_factory-0.1.1.dist-info/entry_points.txt
databricks_dbt_factory-0.1.1.dist-info/licenses/LICENSE.txt
databricks_dbt_factory-0.1.1.dist-info/RECORD
