Metadata-Version: 2.4
Name: databricks-dbt-factory
Version: 0.1.1
Summary: Databricks dbt factory library for creating Databricks Job definition where individual models are run as separate tasks.
Project-URL: Documentation, https://github.com/mwojtyczka/databricks-dbt-factory#readme
Project-URL: Issues, https://github.com/mwojtyczka/databricks-dbt-factory/issues
Project-URL: Source, https://github.com/mwojtyczka/databricks-dbt-factory
Author-email: Marcin Wojtyczka <marcin.wojtyczka@databricks.com>
License-Expression: MIT
License-File: LICENSE.txt
Keywords: Databricks,dbt
Classifier: Development Status :: 4 - Beta
Classifier: Environment :: Console
Classifier: Framework :: Pytest
Classifier: Intended Audience :: Developers
Classifier: Intended Audience :: System Administrators
Classifier: Operating System :: MacOS
Classifier: Operating System :: Microsoft :: Windows
Classifier: Programming Language :: Python
Classifier: Programming Language :: Python :: 3.10
Classifier: Programming Language :: Python :: 3.11
Classifier: Programming Language :: Python :: 3.12
Classifier: Programming Language :: Python :: Implementation :: CPython
Classifier: Programming Language :: Python :: Implementation :: PyPy
Classifier: Topic :: Software Development :: Libraries
Classifier: Topic :: Utilities
Requires-Python: >=3.10
Requires-Dist: pyyaml~=6.0.1
